flask_adapter
